ampyc/__init__.py
ampyc/noise.py
ampyc/typing.py
ampyc/controllers/__init__.py
ampyc/controllers/constraint_tightening_rmpc.py
ampyc/controllers/constraint_tightening_smpc.py
ampyc/controllers/controller_base.py
ampyc/controllers/if_smpc.py
ampyc/controllers/mpc.py
ampyc/controllers/nonlinear_mpc.py
ampyc/controllers/nonlinear_robust_mpc.py
ampyc/controllers/ri_smpc.py
ampyc/controllers/robust_mpc.py
ampyc/params/__init__.py
ampyc/params/params_base.py
ampyc/params/params_mpc.py
ampyc/params/params_nmpc.py
ampyc/params/params_rmpc.py
ampyc/params/params_rmpc_smpc.py
ampyc/params/params_rnmpc.py
ampyc/params/params_smpc.py
ampyc/params/params_test.py
ampyc/plotting/__init__.py
ampyc/plotting/plot_quad_set.py
ampyc/plotting/plot_tubes.py
ampyc/plotting/plot_u.py
ampyc/plotting/plot_x.py
ampyc/systems/__init__.py
ampyc/systems/linear_affine_system.py
ampyc/systems/linear_system.py
ampyc/systems/nonlinear_system.py
ampyc/systems/system_base.py
ampyc/utils/__init__.py
ampyc/utils/helpers.py
ampyc/utils/math.py
ampyc/utils/set_computation.py
ampyc/utils/polytope/LICENSE
ampyc/utils/polytope/polytope.py
ampyc-0.0.2.dist-info/METADATA
ampyc-0.0.2.dist-info/WHEEL
ampyc-0.0.2.dist-info/RECORD
