Metadata-Version: 2.4
Name: ampyc
Version: 0.0.2
Summary: Python implementation of various advanced MPC algorithms
Project-URL: Homepage, https://example.com
Project-URL: Documentation, https://github.com/IntelligentControlSystems/ampyc/tree/main/notes
Project-URL: Repository, https://github.com/IntelligentControlSystems/ampyc
Project-URL: Bug Tracker, https://github.com/IntelligentControlSystems/ampyc/issues
Author: Mike Zhang
Author-email: Jerome Sieber <jsieber@ethz.ch>, Alexandre Didier <adidier@ethz.ch>, Rahel Rickenbach <rrahel@ethz.ch>
Maintainer-email: Jerome Sieber <jsieber@ethz.ch>
License-Expression: MIT
Keywords: Control Framework,MPC,Robust MPC,Stochastic MPC
Classifier: Development Status :: 3 - Alpha
Classifier: Intended Audience :: Developers
Classifier: Intended Audience :: Science/Research
Classifier: Programming Language :: Python :: 3 :: Only
Requires-Python: >=3.10
Requires-Dist: casadi
Requires-Dist: cvxpy
Requires-Dist: ecos
Requires-Dist: jupyter
Requires-Dist: matplotlib
Requires-Dist: numpy
Requires-Dist: polytope
Requires-Dist: pyqt6
Requires-Dist: scipy
Requires-Dist: tqdm
Provides-Extra: cvxopt
Requires-Dist: cvxopt; extra == 'cvxopt'
